autovf/__init__.py
autovf/api.py
autovf/autovf.py
autovf/enums.py
autovf/logger.py
autovf/metrics.py
autovf/params.py
autovf/predict.py
autovf/schemas.py
autovf/utils.py
autovf/cli/__init__.py
autovf/cli/autovf.py
autovf/cli/predict.py
autovf/cli/serve.py
autovf/cli/train.py
autovf-0.0.6.dist-info/LICENSE
autovf-0.0.6.dist-info/METADATA
autovf-0.0.6.dist-info/WHEEL
autovf-0.0.6.dist-info/entry_points.txt
autovf-0.0.6.dist-info/top_level.txt
autovf-0.0.6.dist-info/RECORD
